ALU/MUX3.v
module MUX3(choice,in0,in1,in2,res);
input[1:0] choice;
input [31:0]in0,in1,in2;
//wire tmp;
output  reg[31:0] res;

/*MUX2(
		.choice(choice[1]),
		.in1(in2),
		.in0(in1),
		.res(tmp)
);
MUX2(
		.choice(choice[0]),
		.in1(tmp),
		.in0(in0),
		.res(res)
);*/
always@(*)
case(choice)
	2'b00:
		res=in0;
	2'b01:
		res=in1;
	2'b10:
		res=in2;
	default:
		res=32'bz;
endcase
endmodule

ALU/OR_32.v
module OR_32(A,B,res);
input[31:0] A,B;
output reg[31:0]res;
always@(*)
	res=A|B;
endmodule

ALU/MUX2_32.v
module MUX2_32
(
    input  wire[31:0]  in0,     //Data
    input  wire[31:0] in1,     //Data 
    input  wire choice,    //High: in1 ;Low: in0
    output reg[31:0] res  
);
always@(choice or in0 or in1)
    if(!choice)  res=in0;
    else     res=in1;
endmodule

ALU/MUX2_1.v
module MUX2_1
(
    input  wire  in0,     //Data
    input  wire in1,     //Data 
    input  wire choice,    //High: in1 ;Low: in0
    output reg res  
);
always@(choice or in0 or in1)
    if(!choice)  res=in0;
    else     res=in1;
endmodule

ALU/Adder_32.v
module Adder_32(A,B,cin,Add_Carry,Add_Overflow,Add_Sign,Add_Result,Zero);
input[31:0] A,B;
input cin;
output reg [31:0] Add_Result;
output reg Add_Carry,Add_Overflow,Add_Sign,Zero;
always @(*)
	begin		
	if(cin==1'b1)
	{Add_Carry,Add_Result}=A+B;
	else
	{Add_Carry,Add_Result}=A-B;
	Add_Overflow=((A[31]==B[31])&&(~Add_Result[31]==A[31]))?1'b1:1'b0;
	Add_Sign=Add_Result[31];
	if(Add_Result==0)
		Zero=1'b1;
	else	
		Zero=1'b0;
	end
endmodule

ALU/Ctr.v
module Ctr( ALUctr,SUBctr,OPctr,SIGctr,OVctr);
input [2:0] ALUctr;
output reg SUBctr,OVctr,SIGctr;
output reg[1:0] OPctr;


always@(*)
begin
	case(ALUctr)
	//addu
        3'b000:
            begin
            SUBctr=1'b0;
				OVctr=1'b0;
				SIGctr=1'b0;
				OPctr=2'b00;
            end
				
	//add
        3'b001:
            begin
				SUBctr=1'b0;
				OVctr=1'b1;
				SIGctr=1'b0;
				OPctr=2'b00;
            end
				
	//or
        3'b010:
            begin
            SUBctr=1'b0;
				OVctr=1'b0;
				SIGctr=1'b0;
				OPctr=2'b01;
            end
	//未用
			/*3'b011:
				begin
				end*/
	//subu
        3'b100:
            begin
				SUBctr=1'b1;
				OVctr=1'b0;
				SIGctr=1'b0;
				OPctr=2'b00;
            end
        
   //sub
        3'b101:
            begin
				SUBctr=1'b1;
				OVctr=1'b1;
				SIGctr=1'b0;
				OPctr=2'b00;
            end
		  //sltu
        3'b110:
            begin
				SUBctr=1'b1;
				OVctr=1'b0;
				SIGctr=1'b0;
				OPctr=2'b10;
            end
        //slt
        3'b111:
            begin                        
				SUBctr=1'b1;
				OVctr=1'b0;
				SIGctr=1'b1;
				OPctr=2'b10;
           end 
			  
			  default:
			  begin                        
				SUBctr=1'b0;
				OVctr=1'b0;
				SIGctr=1'b0;
				OPctr=2'b0;
           end 
    endcase
end
endmodule

ALU/ALU.v
`include "Adder_32.v"
`include "Ctr.v"
`include "MUX2_1.v"
`include "MUX2_32.v"
`include "OR_32.v"
`include "MUX3.v"

module ALU(A,B,Result,Zero,Overflow,Add_Result,Less_Result,OR_Result,ALUctr);
input[31:0] A,B;
input[2:0] ALUctr;

output wire[31:0] Result;
output wire Zero,Overflow;
output wire[31:0] Add_Result,Less_Result,OR_Result;

wire Add_Carry,Add_Overflow,Add_Sign;
wire Less;
wire SUBctr,OVctr,SIGctr;
wire[1:0] OPctr;
Ctr   ctr
		(
		.ALUctr(ALUctr),
		.SUBctr(SUBctr),
		.OVctr(OVctr),
		.SIGctr(SIGctr),
		.OPctr(OPctr)
		);

Adder_32 adder_32
		(
		.A(A),
		.B(B),
		.cin(SUBctr),
		.Add_Carry(Add_Carry),
		.Add_Overflow(Add_Overflow),
		.Add_Sign(Add_Sign),
		.Add_Result(Add_Result),
		.Zero(Zero)
		);

MUX2_1  mux2_1
		(
		.choice(SIGctr),
		.in0(SUBctr^Add_Carry),
		.in1(Add_Overflow^Add_Sign),
		.res(Less)
	);
MUX2_32  mux2_32
		(
		.choice(Less),
		.in0(32'b0),
		.in1(32'b1),
		.res(Less_Result)
	);
	
OR_32  or_32
		(
		.A(A),
		.B(B),
		.res(OR_Result)
);

MUX3  mux3(
		.choice(OPctr),
		.in0(Add_Result),
		.in1(OR_Result),
		.in2(Less_Result),
		.res(Result)
	);
assign Overflow=Add_Overflow&OVctr;
endmodule

ALU/tb_ALU.v
`timescale  1ns / 1ps
`include "ALU.v"
module tb_ALU;

// ALU Parameters
parameter PERIOD  = 10;


// ALU Inputs
reg   [31:0]  A                            = 0 ;
reg   [31:0]  B                            = 0 ;
reg   [2:0]  ALUctr                        = 0 ;

// ALU Outputs
wire[31:0] Result                          ;
wire  Zero                                 ;
wire  Overflow                             ;
wire[31:0]Add_Result                       ;
wire[31:0]Less_Result                      ;
wire[31:0]OR_Result                        ;


ALU  u_ALU (
    .A                       ( A                      [31:0] ),
    .B                       ( B                      [31:0] ),
    .ALUctr                  ( ALUctr                 [2:0]  ),
    .Result                  ( Result                        ),
    .Zero                    ( Zero                          ),
    .Overflow                ( Overflow                      ),
    .Add_Result              (Add_Result                     ),
    .Less_Result             ( Less_Result                   ),
    .OR_Result               ( OR_Result                     )
);

initial
begin
    $dumpfile("tb_ALU.vcd");
    $dumpvars;
      //addu          
	    ALUctr=3'b000;
         A=32'hf2340000;
         B=32'h80000000;
    #20  A=32'h7fffffff;
         B=32'h70000001;
    #20  A=32'hffffffff;
         B=32'h00000001;
    //add
         ALUctr=3'b001;
         A=32'hf2340000;
         B=32'h80000000;
    #20  A=32'h7fffffff;
         B=32'h70000001;
    #20  A=32'h7fffffff;
         B=32'hf0000001;
    #20  A=32'hffffffff;
         B=32'h00000001;
			
	//or
    #20  ALUctr=3'b010;        
         A=32'h00000000;
         B=32'h00000000;
    #20  A=32'h7fffffff;
         B=32'hf0000001;
    
    //subu
    #20  ALUctr=3'b100;        
         A=32'h72340000;
         B=32'h60000000;
    #20  A=32'h7fffffff;
         B=32'hf0000001;
    #20  A=32'hffffffff;
         B=32'hffffffff;
    #20  A=32'hf0000000;
         B=32'h0fffffff; 
			
	 //sub    
    #20  ALUctr=3'b101;        
         A=32'h72340000;
         B=32'h60000000;
    #20  A=32'h7fffffff;
         B=32'hf0000001;
    #20  A=32'hf00fffff;
         B=32'h7ffffff1;
    #20  A=32'hffffffff;
         B=32'hffffffff;
    #20  A=32'hf0000000;
         B=32'h0fffffff;
     //sltu
    #20  ALUctr=3'b110;        
         A=32'h72340000;
         B=32'hf0000000;
    #20  A=32'h7000000f;
         B=32'h7f000001;
    #20  A=32'hf0001231;
         B=32'h7ac34545;
    //slt
    #20  ALUctr=3'b111;        
         A=32'h72340000;
         B=32'hf0000000;
    #20  A=32'h7000000f;
         B=32'h7f000001;
    #20  A=32'hf0001231;
         B=32'h7ac34545;
    $finish;
end

endmodule

ALU/tb_ALU.vcd
$date
	Mon Jan 09 10:18:25 2023
$end
$version
	Icarus Verilog
$end
$timescale
	1ps
$end
$scope module tb_ALU $end
$var wire 1 ! Zero $end
$var wire 32 " Result [31:0] $end
$var wire 1 # Overflow $end
$var wire 32 $ OR_Result [31:0] $end
$var wire 32 % Less_Result [31:0] $end
$var wire 32 & Add_Result [31:0] $end
$var reg 32 ' A [31:0] $end
$var reg 3 ( ALUctr [2:0] $end
$var reg 32 ) B [31:0] $end
$scope module u_ALU $end
$var wire 32 * A [31:0] $end
$var wire 3 + ALUctr [2:0] $end
$var wire 32 , B [31:0] $end
$var wire 1 # Overflow $end
$var wire 1 ! Zero $end
$var wire 1 - SUBctr $end
$var wire 1 . SIGctr $end
$var wire 32 / Result [31:0] $end
$var wire 1 0 OVctr $end
$var wire 32 1 OR_Result [31:0] $end
$var wire 2 2 OPctr [1:0] $end
$var wire 32 3 Less_Result [31:0] $end
$var wire 1 4 Less $end
$var wire 1 5 Add_Sign $end
$var wire 32 6 Add_Result [31:0] $end
$var wire 1 7 Add_Overflow $end
$var wire 1 8 Add_Carry $end
$scope module adder_32 $end
$var wire 32 9 A [31:0] $end
$var wire 32 : B [31:0] $end
$var wire 1 - cin $end
$var reg 1 8 Add_Carry $end
$var reg 1 7 Add_Overflow $end
$var reg 32 ; Add_Result [31:0] $end
$var reg 1 5 Add_Sign $end
$var reg 1 ! Zero $end
$upscope $end
$scope module ctr $end
$var wire 3 < ALUctr [2:0] $end
$var reg 2 = OPctr [1:0] $end
$var reg 1 0 OVctr $end
$var reg 1 . SIGctr $end
$var reg 1 - SUBctr $end
$upscope $end
$scope module mux2_1 $end
$var wire 1 . choice $end
$var wire 1 > in0 $end
$var wire 1 ? in1 $end
$var reg 1 4 res $end
$upscope $end
$scope module mux2_32 $end
$var wire 1 4 choice $end
$var wire 32 @ in0 [31:0] $end
$var wire 32 A in1 [31:0] $end
$var reg 32 B res [31:0] $end
$upscope $end
$scope module mux3 $end
$var wire 2 C choice [1:0] $end
$var wire 32 D in0 [31:0] $end
$var wire 32 E in2 [31:0] $end
$var wire 32 F in1 [31:0] $end
$var reg 32 G res [31:0] $end
$upscope $end
$scope module or_32 $end
$var wire 32 H A [31:0] $end
$var wire 32 I B [31:0] $end
$var reg 32 J res [31:0] $end
$upscope $end
$upscope $end
$upscope $end
$enddefinitions $end
#0
$dumpvars
b11110010001101000000000000000000 J
b10000000000000000000000000000000 I
b11110010001101000000000000000000 H
b1110010001101000000000000000000 G
b11110010001101000000000000000000 F
b0 E
b1110010001101000000000000000000 D
b0 C
b0 B
b1 A
b0 @
1?
0>
b0 =
b0 <
b1110010001101000000000000000000 ;
b10000000000000000000000000000000 :
b11110010001101000000000000000000 9
08
17
b1110010001101000000000000000000 6
05
04
b0 3
b0 2
b11110010001101000000000000000000 1
00
b1110010001101000000000000000000 /
0.
0-
b10000000000000000000000000000000 ,
b0 +
b11110010001101000000000000000000 *
b10000000000000000000000000000000 )
b0 (
b11110010001101000000000000000000 '
b1110010001101000000000000000000 &
b0 %
b11110010001101000000000000000000 $
0#
b1110010001101000000000000000000 "
0!
$end
#20000
0?
b1111111111111111111111111110 "
b1111111111111111111111111110 /
b1111111111111111111111111110 G
07
b1111111111111111111111111110 &
b1111111111111111111111111110 6
b1111111111111111111111111110 ;
b1111111111111111111111111110 D
b1111111111111111111111111111111 $
b1111111111111111111111111111111 1
b1111111111111111111111111111111 F
b1111111111111111111111111111111 J
b1110000000000000000000000000001 )
b1110000000000000000000000000001 ,
b1110000000000000000000000000001 :
b1110000000000000000000000000001 I
b1111111111111111111111111111111 '
b1111111111111111111111111111111 *
b1111111111111111111111111111111 9
b1111111111111111111111111111111 H
#40000
1#
1?
b1110010001101000000000000000000 "
b1110010001101000000000000000000 /
b1110010001101000000000000000000 G
10
17
b1110010001101000000000000000000 &
b1110010001101000000000000000000 6
b1110010001101000000000000000000 ;
b1110010001101000000000000000000 D
b11110010001101000000000000000000 $
b11110010001101000000000000000000 1
b11110010001101000000000000000000 F
b11110010001101000000000000000000 J
b1 (
b1 +
b1 <
b10000000000000000000000000000000 )
b10000000000000000000000000000000 ,
b10000000000000000000000000000000 :
b10000000000000000000000000000000 I
b11110010001101000000000000000000 '
b11110010001101000000000000000000 *
b11110010001101000000000000000000 9
b11110010001101000000000000000000 H
#60000
0#
0?
b1111111111111111111111111110 "
b1111111111111111111111111110 /
b1111111111111111111111111110 G
07
b1111111111111111111111111110 &
b1111111111111111111111111110 6
b1111111111111111111111111110 ;
b1111111111111111111111111110 D
b1111111111111111111111111111111 $
b1111111111111111111111111111111 1
b1111111111111111111111111111111 F
b1111111111111111111111111111111 J
b1110000000000000000000000000001 )
b1110000000000000000000000000001 ,
b1110000000000000000000000000001 :
b1110000000000000000000000000001 I
b1111111111111111111111111111111 '
b1111111111111111111111111111111 *
b1111111111111111111111111111111 9
b1111111111111111111111111111111 H
#80000
b1 %
b1 3
b1 B
b1 E
14
1?
1>
b10001111111111111111111111111110 "
b10001111111111111111111111111110 /
b10001111111111111111111111111110 G
15
18
b10001111111111111111111111111110 &
b10001111111111111111111111111110 6
b10001111111111111111111111111110 ;
b10001111111111111111111111111110 D
b11111111111111111111111111111111 $
b11111111111111111111111111111111 1
b11111111111111111111111111111111 F
b11111111111111111111111111111111 J
b11110000000000000000000000000001 )
b11110000000000000000000000000001 ,
b11110000000000000000000000000001 :
b11110000000000000000000000000001 I
#100000
b0 %
b0 3
b0 B
b0 E
04
0>
b11111111111111111111111111111110 "
b11111111111111111111111111111110 /
b11111111111111111111111111111110 G
08
b11111111111111111111111111111110 &
b11111111111111111111111111111110 6
b11111111111111111111111111111110 ;
b11111111111111111111111111111110 D
b1 )
b1 ,
b1 :
b1 I
b11111111111111111111111111111111 '
b11111111111111111111111111111111 *
b11111111111111111111111111111111 9
b11111111111111111111111111111111 H
#120000
0?
b0 "
b0 /
b0 G
1!
05
b0 &
b0 6
b0 ;
b0 D
b0 $
b0 1
b0 F
b0 J
b1 2
b1 =
b1 C
00
b0 )
b0 ,
b0 :
b0 I
b0 '
b0 *
b0 9
b0 H
b10 (
b10 +
b10 <
#140000
b1 %
b1 3
b1 B
b1 E
14
1?
1>
b11111111111111111111111111111111 "
b11111111111111111111111111111111 /
b11111111111111111111111111111111 G
0!
15
18
b10001111111111111111111111111110 &
b10001111111111111111111111111110 6
b10001111111111111111111111111110 ;
b10001111111111111111111111111110 D
b11111111111111111111111111111111 $
b11111111111111111111111111111111 1
b11111111111111111111111111111111 F
b11111111111111111111111111111111 J
b11110000000000000000000000000001 )
b11110000000000000000000000000001 ,
b11110000000000000000000000000001 :
b11110000000000000000000000000001 I
b1111111111111111111111111111111 '
b1111111111111111111111111111111 *
b1111111111111111111111111111111 9
b1111111111111111111111111111111 H
#160000
0?
b11010010001101000000000000000000 "
b11010010001101000000000000000000 /
b11010010001101000000000000000000 G
17
08
b11010010001101000000000000000000 &
b11010010001101000000000000000000 6
b11010010001101000000000000000000 ;
b11010010001101000000000000000000 D
b1110010001101000000000000000000 $
b1110010001101000000000000000000 1
b1110010001101000000000000000000 F
b1110010001101000000000000000000 J
b0 2
b0 =
b0 C
1-
b1100000000000000000000000000000 )
b1100000000000000000000000000000 ,
b1100000000000000000000000000000 :
b1100000000000000000000000000000 I
b1110010001101000000000000000000 '
b1110010001101000000000000000000 *
b1110010001101000000000000000000 9
b1110010001101000000000000000000 H
b100 (
b100 +
b100 <
#180000
b0 %
b0 3
b0 B
b0 E
04
0>
b1110000000000000000000000000000 "
b1110000000000000000000000000000 /
b1110000000000000000000000000000 G
05
07
18
b1110000000000000000000000000000 &
b1110000000000000000000000000000 6
b1110000000000000000000000000000 ;
b1110000000000000000000000000000 D
b11111111111111111111111111111111 $
b11111111111111111111111111111111 1
b11111111111111111111111111111111 F
b11111111111111111111111111111111 J
b11110000000000000000000000000001 )
b11110000000000000000000000000001 ,
b11110000000000000000000000000001 :
b11110000000000000000000000000001 I
b1111111111111111111111111111111 '
b1111111111111111111111111111111 *
b1111111111111111111111111111111 9
b1111111111111111111111111111111 H
#200000
1?
b11111111111111111111111111111110 "
b11111111111111111111111111111110 /
b11111111111111111111111111111110 G
15
b11111111111111111111111111111110 &
b11111111111111111111111111111110 6
b11111111111111111111111111111110 ;
b11111111111111111111111111111110 D
b11111111111111111111111111111111 )
b11111111111111111111111111111111 ,
b11111111111111111111111111111111 :
b11111111111111111111111111111111 I
b11111111111111111111111111111111 '
b11111111111111111111111111111111 *
b11111111111111111111111111111111 9
b11111111111111111111111111111111 H
#220000
b1 %
b1 3
b1 B
b1 E
14
1>
b11111111111111111111111111111111 "
b11111111111111111111111111111111 /
b11111111111111111111111111111111 G
08
b11111111111111111111111111111111 &
b11111111111111111111111111111111 6
b11111111111111111111111111111111 ;
b11111111111111111111111111111111 D
b1111111111111111111111111111 )
b1111111111111111111111111111 ,
b1111111111111111111111111111 :
b1111111111111111111111111111 I
b11110000000000000000000000000000 '
b11110000000000000000000000000000 *
b11110000000000000000000000000000 9
b11110000000000000000000000000000 H
#240000
0?
b11010010001101000000000000000000 "
b11010010001101000000000000000000 /
b11010010001101000000000000000000 G
1#
17
b11010010001101000000000000000000 &
b11010010001101000000000000000000 6
b11010010001101000000000000000000 ;
b11010010001101000000000000000000 D
b1110010001101000000000000000000 $
b1110010001101000000000000000000 1
b1110010001101000000000000000000 F
b1110010001101000000000000000000 J
10
b1100000000000000000000000000000 )
b1100000000000000000000000000000 ,
b1100000000000000000000000000000 :
b1100000000000000000000000000000 I
b1110010001101000000000000000000 '
b1110010001101000000000000000000 *
b1110010001101000000000000000000 9
b1110010001101000000000000000000 H
b101 (
b101 +
b101 <
#260000
b0 %
b0 3
b0 B
b0 E
04
0#
0>
b1110000000000000000000000000000 "
b1110000000000000000000000000000 /
b1110000000000000000000000000000 G
05
07
18
b1110000000000000000000000000000 &
b1110000000000000000000000000000 6
b1110000000000000000000000000000 ;
b1110000000000000000000000000000 D
b11111111111111111111111111111111 $
b11111111111111111111111111111111 1
b11111111111111111111111111111111 F
b11111111111111111111111111111111 J
b11110000000000000000000000000001 )
b11110000000000000000000000000001 ,
b11110000000000000000000000000001 :
b11110000000000000000000000000001 I
b1111111111111111111111111111111 '
b1111111111111111111111111111111 *
b1111111111111111111111111111111 9
b1111111111111111111111111111111 H
#280000
b1110000000011111111111111110000 "
b1110000000011111111111111110000 /
b1110000000011111111111111110000 G
b1110000000011111111111111110000 &
b1110000000011111111111111110000 6
b1110000000011111111111111110000 ;
b1110000000011111111111111110000 D
b1111111111111111111111111110001 )
b1111111111111111111111111110001 ,
b1111111111111111111111111110001 :
b1111111111111111111111111110001 I
b11110000000011111111111111111111 '
b11110000000011111111111111111111 *
b11110000000011111111111111111111 9
b11110000000011111111111111111111 H
#300000
1?
b11111111111111111111111111111110 "
b11111111111111111111111111111110 /
b11111111111111111111111111111110 G
15
b11111111111111111111111111111110 &
b11111111111111111111111111111110 6
b11111111111111111111111111111110 ;
b11111111111111111111111111111110 D
b11111111111111111111111111111111 )
b11111111111111111111111111111111 ,
b11111111111111111111111111111111 :
b11111111111111111111111111111111 I
b11111111111111111111111111111111 '
b11111111111111111111111111111111 *
b11111111111111111111111111111111 9
b11111111111111111111111111111111 H
#320000
b1 %
b1 3
b1 B
b1 E
14
1>
b11111111111111111111111111111111 "
b11111111111111111111111111111111 /
b11111111111111111111111111111111 G
08
b11111111111111111111111111111111 &
b11111111111111111111111111111111 6
b11111111111111111111111111111111 ;
b11111111111111111111111111111111 D
b1111111111111111111111111111 )
b1111111111111111111111111111 ,
b1111111111111111111111111111 :
b1111111111111111111111111111 I
b11110000000000000000000000000000 '
b11110000000000000000000000000000 *
b11110000000000000000000000000000 9
b11110000000000000000000000000000 H
#340000
b0 %
b0 3
b0 B
b0 E
04
0?
0>
b0 "
b0 /
b0 G
05
18
b1100010001101000000000000000000 &
b1100010001101000000000000000000 6
b1100010001101000000000000000000 ;
b1100010001101000000000000000000 D
b11110010001101000000000000000000 $
b11110010001101000000000000000000 1
b11110010001101000000000000000000 F
b11110010001101000000000000000000 J
b10 2
b10 =
b10 C
00
b11110000000000000000000000000000 )
b11110000000000000000000000000000 ,
b11110000000000000000000000000000 :
b11110000000000000000000000000000 I
b1110010001101000000000000000000 '
b1110010001101000000000000000000 *
b1110010001101000000000000000000 9
b1110010001101000000000000000000 H
b110 (
b110 +
b110 <
#360000
b1 "
b1 /
b1 G
b1 %
b1 3
b1 B
b1 E
14
1>
15
17
08
b11101111000000000000000000010000 &
b11101111000000000000000000010000 6
b11101111000000000000000000010000 ;
b11101111000000000000000000010000 D
b1111111000000000000000000001111 $
b1111111000000000000000000001111 1
b1111111000000000000000000001111 F
b1111111000000000000000000001111 J
b1111111000000000000000000000001 )
b1111111000000000000000000000001 ,
b1111111000000000000000000000001 :
b1111111000000000000000000000001 I
b1110000000000000000000000001111 '
b1110000000000000000000000001111 *
b1110000000000000000000000001111 9
b1110000000000000000000000001111 H
#380000
b0 "
b0 /
b0 G
b0 %
b0 3
b0 B
b0 E
04
0>
05
07
18
b1101010110000110101011101110110 &
b1101010110000110101011101110110 6
b1101010110000110101011101110110 ;
b1101010110000110101011101110110 D
b11111010110000110101011101110101 $
b11111010110000110101011101110101 1
b11111010110000110101011101110101 F
b11111010110000110101011101110101 J
b1111010110000110100010101000101 )
b1111010110000110100010101000101 ,
b1111010110000110100010101000101 :
b1111010110000110100010101000101 I
b11110000000000000001001000110001 '
b11110000000000000001001000110001 *
b11110000000000000001001000110001 9
b11110000000000000001001000110001 H
#400000
b1100010001101000000000000000000 &
b1100010001101000000000000000000 6
b1100010001101000000000000000000 ;
b1100010001101000000000000000000 D
b11110010001101000000000000000000 $
b11110010001101000000000000000000 1
b11110010001101000000000000000000 F
b11110010001101000000000000000000 J
1.
b11110000000000000000000000000000 )
b11110000000000000000000000000000 ,
b11110000000000000000000000000000 :
b11110000000000000000000000000000 I
b1110010001101000000000000000000 '
b1110010001101000000000000000000 *
b1110010001101000000000000000000 9
b1110010001101000000000000000000 H
b111 (
b111 +
b111 <
#420000
1>
15
17
08
b11101111000000000000000000010000 &
b11101111000000000000000000010000 6
b11101111000000000000000000010000 ;
b11101111000000000000000000010000 D
b1111111000000000000000000001111 $
b1111111000000000000000000001111 1
b1111111000000000000000000001111 F
b1111111000000000000000000001111 J
b1111111000000000000000000000001 )
b1111111000000000000000000000001 ,
b1111111000000000000000000000001 :
b1111111000000000000000000000001 I
b1110000000000000000000000001111 '
b1110000000000000000000000001111 *
b1110000000000000000000000001111 9
b1110000000000000000000000001111 H
#440000
0>
05
07
18
b1101010110000110101011101110110 &
b1101010110000110101011101110110 6
b1101010110000110101011101110110 ;
b1101010110000110101011101110110 D
b11111010110000110101011101110101 $
b11111010110000110101011101110101 1
b11111010110000110101011101110101 F
b11111010110000110101011101110101 J
b1111010110000110100010101000101 )
b1111010110000110100010101000101 ,
b1111010110000110100010101000101 :
b1111010110000110100010101000101 I
b11110000000000000001001000110001 '
b11110000000000000001001000110001 *
b11110000000000000001001000110001 9
b11110000000000000001001000110001 H
